do/__init__.py
do/assist.py
do/config.json
do/config.py
do/do.py
do/licenses.py
do/skeleton.py
do/skeleton_.py
do/template_config.py
do/__pycache__/__init__.cpython-36.pyc
do/__pycache__/assist.cpython-36.pyc
do/__pycache__/assist_skeleton.cpython-36.pyc
do/__pycache__/config.cpython-36.pyc
do/__pycache__/do.cpython-36.pyc
do/__pycache__/empty_skeleton.cpython-36.pyc
do/__pycache__/licenses.cpython-36.pyc
do/__pycache__/setup_config.cpython-36.pyc
do/__pycache__/skeleton.cpython-36.pyc
do/__pycache__/structure.cpython-36.pyc
do/__pycache__/template_config.cpython-36.pyc
do/__pycache__/test.cpython-36.pyc
do/__pycache__/test_template.cpython-36.pyc
do/templates/default_structure.json
do/templates/django.json
do/templates/flask.json
do/templates/pymin.json
do/templates/template_authors.txt
do/templates/template_gitignore.txt
do/templates/template_setup.txt
do/templates/licenses/index.json
do/templates/licenses/template_GNU_AGPLv3.txt
do/templates/licenses/template_GNU_LGPLv3.txt
do/templates/licenses/template_apache2.txt
do/templates/licenses/template_bsd.txt
do/templates/licenses/template_gnu3.txt
do/templates/licenses/template_mit.txt
do/templates/licenses/template_mozilla_PL2.txt
do/templates/licenses/template_unlicense.txt
do_pack-0.1.4.dist-info/DESCRIPTION.rst
do_pack-0.1.4.dist-info/METADATA
do_pack-0.1.4.dist-info/RECORD
do_pack-0.1.4.dist-info/WHEEL
do_pack-0.1.4.dist-info/entry_points.txt
do_pack-0.1.4.dist-info/metadata.json
do_pack-0.1.4.dist-info/top_level.txt
