Metadata-Version: 2.0
Name: do-pack
Version: 0.1.4
Summary: A command-line tool to create python packages
Home-page: https://github.com/wilfredinni/do-pack
Author: Carlos Montecinos Geisse
Author-email: carlos.w.montecinos@gmail.com
License: MIT License
Platform: UNKNOWN
Classifier: Development Status :: 2 - Pre-Alpha
Classifier: Intended Audience :: Developers
Classifier: License :: OSI Approved :: MIT License
Classifier: Natural Language :: English
Classifier: Programming Language :: Python :: 3
Classifier: Programming Language :: Python :: 3.4
Classifier: Programming Language :: Python :: 3.5
Classifier: Programming Language :: Python :: 3.6
Requires-Python: >=3
Requires-Dist: click
